{
  "collectionName": "components_carousel_caorusels",
  "info": {
    "displayName": "caorusel",
    "icon": "archive",
    "description": ""
  },
  "options": {},
  "attributes": {
    "image": {
      "type": "media",
      "multiple": false,
      "required": true,
      "allowedTypes": [
        "images",
        "files",
        "videos",
        "audios"
      ]
    },
    "title": {
      "type": "string",
      "required": true
    },
    "context": {
      "type": "string",
      "required": true
    },
    "vn_title": {
      "type": "string",
      "required": true
    },
    "vn_context": {
      "type": "string",
      "required": true
    },
    "cn_title": {
      "type": "string",
      "required": true
    },
    "cn_context": {
      "type": "text",
      "required": true
    },
    "zh_title": {
      "type": "string",
      "required": true
    },
    "zh_context": {
      "type": "string",
      "required": true
    }
  }
}
